{"url": "https://www.sec.gov/Archives/edgar/data/1067983/000095012320009058/960.xml", "stored_at": 1761637768, "headers": {"accept-ranges": "bytes", "content-encoding": "gzip", "content-type": "text/xml", "etag": "\"9ce9d8a7c3bbcbb129d586f477d498ca-gzip\"", "last-modified": "Fri, 14 Aug 2020 20:02:57 GMT", "x-amz-id-2": "7cuR1hd9O8jcXAJq2q1MTnb/Je/018/o8YdngK/W+cOMpQ8hEhfmjsdUnQrYitYDuZO2MrsZ1phYkk7V7s59r4JPbQTz/hs/", "x-amz-meta-mode": "33188", "x-amz-replication-status": "COMPLETED", "x-amz-request-id": "NAQKMWYDTJYSYF91", "x-amz-version-id": "J.rtp6Q9L12WxSCzm.PaAcCmY_P48ON.", "x-content-type-options": "nosniff", "x-frame-options": "SAMEORIGIN", "x-xss-protection": "1; mode=block", "content-length": "3987", "date": "Tue, 28 Oct 2025 07:49:28 GMT", "connection": "keep-alive", "vary": "Accept-Encoding", "strict-transport-security": "max-age=31536000 ; includeSubDomains ; preload"}, "etag": "\"9ce9d8a7c3bbcbb129d586f477d498ca-gzip\"", "last_modified": "Fri, 14 Aug 2020 20:02:57 GMT", "status": 200}